{"average_history": [{"win_rate_mcts": 1.0, "win_rate_random": 0.0, "average_game_length": 8.0}, {"win_rate_mcts": 1.0, "win_rate_random": 0.0, "average_game_length": 8.5}, {"win_rate_mcts": 1.0, "win_rate_random": 0.0, "average_game_length": 11.666666666666666}, {"win_rate_mcts": 1.0, "win_rate_random": 0.0, "average_game_length": 12.0}, {"win_rate_mcts": 1.0, "win_rate_random": 0.0, "average_game_length": 15.6}, {"win_rate_mcts": 1.0, "win_rate_random": 0.0, "average_game_length": 14.833333333333334}, {"win_rate_mcts": 1.0, "win_rate_random": 0.0, "average_game_length": 15.0}, {"win_rate_mcts": 1.0, "win_rate_random": 0.0, "average_game_length": 15.75}, {"win_rate_mcts": 1.0, "win_rate_random": 0.0, "average_game_length": 15.777777777777779}, {"win_rate_mcts": 1.0, "win_rate_random": 0.0, "average_game_length": 15.5}, {"win_rate_mcts": 1.0, "win_rate_random": 0.0, "average_game_length": 15.181818181818182}, {"win_rate_mcts": 1.0, "win_rate_random": 0.0, "average_game_length": 14.666666666666666}, {"win_rate_mcts": 1.0, "win_rate_random": 0.0, "average_game_length": 15.538461538461538}, {"win_rate_mcts": 1.0, "win_rate_random": 0.0, "average_game_length": 15.785714285714286}, {"win_rate_mcts": 1.0, "win_rate_random": 0.0, "average_game_length": 15.533333333333333}, {"win_rate_mcts": 1.0, "win_rate_random": 0.0, "average_game_length": 15.25}, {"win_rate_mcts": 1.0, "win_rate_random": 0.0, "average_game_length": 15.294117647058824}, {"win_rate_mcts": 1.0, "win_rate_random": 0.0, "average_game_length": 15.055555555555555}, {"win_rate_mcts": 1.0, "win_rate_random": 0.0, "average_game_length": 14.789473684210526}, {"win_rate_mcts": 1.0, "win_rate_random": 0.0, "average_game_length": 14.9}, {"win_rate_mcts": 1.0, "win_rate_random": 0.0, "average_game_length": 14.666666666666666}, {"win_rate_mcts": 1.0, "win_rate_random": 0.0, "average_game_length": 14.5}, {"win_rate_mcts": 1.0, "win_rate_random": 0.0, "average_game_length": 14.652173913043478}, {"win_rate_mcts": 1.0, "win_rate_random": 0.0, "average_game_length": 14.666666666666666}, {"win_rate_mcts": 1.0, "win_rate_random": 0.0, "average_game_length": 14.56}, {"win_rate_mcts": 1.0, "win_rate_random": 0.0, "average_game_length": 14.884615384615385}, {"win_rate_mcts": 1.0, "win_rate_random": 0.0, "average_game_length": 14.851851851851851}, {"win_rate_mcts": 1.0, "win_rate_random": 0.0, "average_game_length": 14.642857142857142}, {"win_rate_mcts": 1.0, "win_rate_random": 0.0, "average_game_length": 14.758620689655173}, {"win_rate_mcts": 1.0, "win_rate_random": 0.0, "average_game_length": 14.766666666666667}, {"win_rate_mcts": 1.0, "win_rate_random": 0.0, "average_game_length": 14.741935483870968}, {"win_rate_mcts": 1.0, "win_rate_random": 0.0, "average_game_length": 14.6875}, {"win_rate_mcts": 1.0, "win_rate_random": 0.0, "average_game_length": 14.666666666666666}, {"win_rate_mcts": 1.0, "win_rate_random": 0.0, "average_game_length": 14.558823529411764}, {"win_rate_mcts": 1.0, "win_rate_random": 0.0, "average_game_length": 14.6}, {"win_rate_mcts": 1.0, "win_rate_random": 0.0, "average_game_length": 14.555555555555555}, {"win_rate_mcts": 1.0, "win_rate_random": 0.0, "average_game_length": 14.54054054054054}, {"win_rate_mcts": 1.0, "win_rate_random": 0.0, "average_game_length": 14.552631578947368}, {"win_rate_mcts": 1.0, "win_rate_random": 0.0, "average_game_length": 14.384615384615385}, {"win_rate_mcts": 1.0, "win_rate_random": 0.0, "average_game_length": 14.65}, {"win_rate_mcts": 1.0, "win_rate_random": 0.0, "average_game_length": 14.634146341463415}, {"win_rate_mcts": 1.0, "win_rate_random": 0.0, "average_game_length": 14.5}, {"win_rate_mcts": 1.0, "win_rate_random": 0.0, "average_game_length": 14.44186046511628}, {"win_rate_mcts": 1.0, "win_rate_random": 0.0, "average_game_length": 14.409090909090908}, {"win_rate_mcts": 1.0, "win_rate_random": 0.0, "average_game_length": 14.533333333333333}, {"win_rate_mcts": 1.0, "win_rate_random": 0.0, "average_game_length": 14.673913043478262}, {"win_rate_mcts": 1.0, "win_rate_random": 0.0, "average_game_length": 14.53191489361702}, {"win_rate_mcts": 1.0, "win_rate_random": 0.0, "average_game_length": 14.625}, {"win_rate_mcts": 1.0, "win_rate_random": 0.0, "average_game_length": 14.53061224489796}, {"win_rate_mcts": 1.0, "win_rate_random": 0.0, "average_game_length": 14.66}, {"win_rate_mcts": 1.0, "win_rate_random": 0.0, "average_game_length": 14.647058823529411}, {"win_rate_mcts": 1.0, "win_rate_random": 0.0, "average_game_length": 14.538461538461538}, {"win_rate_mcts": 1.0, "win_rate_random": 0.0, "average_game_length": 14.415094339622641}, {"win_rate_mcts": 1.0, "win_rate_random": 0.0, "average_game_length": 14.462962962962964}, {"win_rate_mcts": 1.0, "win_rate_random": 0.0, "average_game_length": 14.49090909090909}, {"win_rate_mcts": 1.0, "win_rate_random": 0.0, "average_game_length": 14.5}, {"win_rate_mcts": 1.0, "win_rate_random": 0.0, "average_game_length": 14.526315789473685}, {"win_rate_mcts": 1.0, "win_rate_random": 0.0, "average_game_length": 14.706896551724139}, {"win_rate_mcts": 1.0, "win_rate_random": 0.0, "average_game_length": 14.627118644067796}, {"win_rate_mcts": 1.0, "win_rate_random": 0.0, "average_game_length": 14.766666666666667}, {"win_rate_mcts": 1.0, "win_rate_random": 0.0, "average_game_length": 14.655737704918034}, {"win_rate_mcts": 1.0, "win_rate_random": 0.0, "average_game_length": 14.564516129032258}, {"win_rate_mcts": 1.0, "win_rate_random": 0.0, "average_game_length": 14.523809523809524}, {"win_rate_mcts": 1.0, "win_rate_random": 0.0, "average_game_length": 14.625}, {"win_rate_mcts": 1.0, "win_rate_random": 0.0, "average_game_length": 14.584615384615384}, {"win_rate_mcts": 1.0, "win_rate_random": 0.0, "average_game_length": 14.530303030303031}, {"win_rate_mcts": 1.0, "win_rate_random": 0.0, "average_game_length": 14.522388059701493}, {"win_rate_mcts": 1.0, "win_rate_random": 0.0, "average_game_length": 14.705882352941176}, {"win_rate_mcts": 1.0, "win_rate_random": 0.0, "average_game_length": 14.81159420289855}, {"win_rate_mcts": 1.0, "win_rate_random": 0.0, "average_game_length": 14.757142857142858}, {"win_rate_mcts": 1.0, "win_rate_random": 0.0, "average_game_length": 14.774647887323944}, {"win_rate_mcts": 1.0, "win_rate_random": 0.0, "average_game_length": 14.75}, {"win_rate_mcts": 1.0, "win_rate_random": 0.0, "average_game_length": 14.657534246575343}, {"win_rate_mcts": 1.0, "win_rate_random": 0.0, "average_game_length": 14.635135135135135}, {"win_rate_mcts": 1.0, "win_rate_random": 0.0, "average_game_length": 14.626666666666667}, {"win_rate_mcts": 1.0, "win_rate_random": 0.0, "average_game_length": 14.552631578947368}, {"win_rate_mcts": 1.0, "win_rate_random": 0.0, "average_game_length": 14.467532467532468}, {"win_rate_mcts": 1.0, "win_rate_random": 0.0, "average_game_length": 14.397435897435898}, {"win_rate_mcts": 1.0, "win_rate_random": 0.0, "average_game_length": 14.316455696202532}, {"win_rate_mcts": 0.9875, "win_rate_random": 0.0125, "average_game_length": 14.3875}, {"win_rate_mcts": 0.9876543209876543, "win_rate_random": 0.012345679012345678, "average_game_length": 14.358024691358025}, {"win_rate_mcts": 0.9878048780487805, "win_rate_random": 0.012195121951219513, "average_game_length": 14.439024390243903}, {"win_rate_mcts": 0.9879518072289156, "win_rate_random": 0.012048192771084338, "average_game_length": 14.385542168674698}, {"win_rate_mcts": 0.9880952380952381, "win_rate_random": 0.011904761904761904, "average_game_length": 14.345238095238095}, {"win_rate_mcts": 0.9882352941176471, "win_rate_random": 0.011764705882352941, "average_game_length": 14.31764705882353}, {"win_rate_mcts": 0.9883720930232558, "win_rate_random": 0.011627906976744186, "average_game_length": 14.279069767441861}, {"win_rate_mcts": 0.9885057471264368, "win_rate_random": 0.011494252873563218, "average_game_length": 14.275862068965518}, {"win_rate_mcts": 0.9886363636363636, "win_rate_random": 0.011363636363636364, "average_game_length": 14.215909090909092}, {"win_rate_mcts": 0.9887640449438202, "win_rate_random": 0.011235955056179775, "average_game_length": 14.168539325842696}, {"win_rate_mcts": 0.9888888888888889, "win_rate_random": 0.011111111111111112, "average_game_length": 14.2}, {"win_rate_mcts": 0.989010989010989, "win_rate_random": 0.01098901098901099, "average_game_length": 14.175824175824175}, {"win_rate_mcts": 0.9891304347826086, "win_rate_random": 0.010869565217391304, "average_game_length": 14.119565217391305}, {"win_rate_mcts": 0.989247311827957, "win_rate_random": 0.010752688172043012, "average_game_length": 14.075268817204302}, {"win_rate_mcts": 0.9893617021276596, "win_rate_random": 0.010638297872340425, "average_game_length": 14.042553191489361}, {"win_rate_mcts": 0.9894736842105263, "win_rate_random": 0.010526315789473684, "average_game_length": 14.0}, {"win_rate_mcts": 0.9895833333333334, "win_rate_random": 0.010416666666666666, "average_game_length": 13.989583333333334}, {"win_rate_mcts": 0.9896907216494846, "win_rate_random": 0.010309278350515464, "average_game_length": 13.969072164948454}, {"win_rate_mcts": 0.9897959183673469, "win_rate_random": 0.01020408163265306, "average_game_length": 14.0}, {"win_rate_mcts": 0.98989898989899, "win_rate_random": 0.010101010101010102, "average_game_length": 13.95959595959596}, {"win_rate_mcts": 0.99, "win_rate_random": 0.01, "average_game_length": 14.07}, {"win_rate_mcts": 0.9900990099009901, "win_rate_random": 0.009900990099009901, "average_game_length": 14.049504950495049}, {"win_rate_mcts": 0.9901960784313726, "win_rate_random": 0.00980392156862745, "average_game_length": 14.098039215686274}, {"win_rate_mcts": 0.9902912621359223, "win_rate_random": 0.009708737864077669, "average_game_length": 14.058252427184467}, {"win_rate_mcts": 0.9903846153846154, "win_rate_random": 0.009615384615384616, "average_game_length": 14.067307692307692}, {"win_rate_mcts": 0.9904761904761905, "win_rate_random": 0.009523809523809525, "average_game_length": 14.085714285714285}, {"win_rate_mcts": 0.9905660377358491, "win_rate_random": 0.009433962264150943, "average_game_length": 14.11320754716981}, {"win_rate_mcts": 0.9906542056074766, "win_rate_random": 0.009345794392523364, "average_game_length": 14.130841121495328}, {"win_rate_mcts": 0.9907407407407407, "win_rate_random": 0.009259259259259259, "average_game_length": 14.268518518518519}, {"win_rate_mcts": 0.9908256880733946, "win_rate_random": 0.009174311926605505, "average_game_length": 14.357798165137615}, {"win_rate_mcts": 0.990909090909091, "win_rate_random": 0.00909090909090909, "average_game_length": 14.418181818181818}, {"win_rate_mcts": 0.990990990990991, "win_rate_random": 0.009009009009009009, "average_game_length": 14.36036036036036}, {"win_rate_mcts": 0.9910714285714286, "win_rate_random": 0.008928571428571428, "average_game_length": 14.330357142857142}, {"win_rate_mcts": 0.9911504424778761, "win_rate_random": 0.008849557522123894, "average_game_length": 14.380530973451327}, {"win_rate_mcts": 0.9912280701754386, "win_rate_random": 0.008771929824561403, "average_game_length": 14.403508771929825}, {"win_rate_mcts": 0.991304347826087, "win_rate_random": 0.008695652173913044, "average_game_length": 14.469565217391304}, {"win_rate_mcts": 0.9913793103448276, "win_rate_random": 0.008620689655172414, "average_game_length": 14.456896551724139}, {"win_rate_mcts": 0.9914529914529915, "win_rate_random": 0.008547008547008548, "average_game_length": 14.435897435897436}, {"win_rate_mcts": 0.9915254237288136, "win_rate_random": 0.00847457627118644, "average_game_length": 14.440677966101696}, {"win_rate_mcts": 0.9915966386554622, "win_rate_random": 0.008403361344537815, "average_game_length": 14.453781512605042}, {"win_rate_mcts": 0.9916666666666667, "win_rate_random": 0.008333333333333333, "average_game_length": 14.441666666666666}, {"win_rate_mcts": 0.9917355371900827, "win_rate_random": 0.008264462809917356, "average_game_length": 14.40495867768595}, {"win_rate_mcts": 0.9836065573770492, "win_rate_random": 0.01639344262295082, "average_game_length": 14.401639344262295}, {"win_rate_mcts": 0.983739837398374, "win_rate_random": 0.016260162601626018, "average_game_length": 14.414634146341463}, {"win_rate_mcts": 0.9838709677419355, "win_rate_random": 0.016129032258064516, "average_game_length": 14.403225806451612}, {"win_rate_mcts": 0.984, "win_rate_random": 0.016, "average_game_length": 14.384}, {"win_rate_mcts": 0.9841269841269841, "win_rate_random": 0.015873015873015872, "average_game_length": 14.38888888888889}, {"win_rate_mcts": 0.984251968503937, "win_rate_random": 0.015748031496062992, "average_game_length": 14.417322834645669}, {"win_rate_mcts": 0.984375, "win_rate_random": 0.015625, "average_game_length": 14.390625}, {"win_rate_mcts": 0.9844961240310077, "win_rate_random": 0.015503875968992248, "average_game_length": 14.387596899224807}, {"win_rate_mcts": 0.9846153846153847, "win_rate_random": 0.015384615384615385, "average_game_length": 14.407692307692308}, {"win_rate_mcts": 0.9847328244274809, "win_rate_random": 0.015267175572519083, "average_game_length": 14.374045801526718}, {"win_rate_mcts": 0.9848484848484849, "win_rate_random": 0.015151515151515152, "average_game_length": 14.363636363636363}, {"win_rate_mcts": 0.9849624060150376, "win_rate_random": 0.015037593984962405, "average_game_length": 14.406015037593985}, {"win_rate_mcts": 0.9850746268656716, "win_rate_random": 0.014925373134328358, "average_game_length": 14.365671641791044}, {"win_rate_mcts": 0.9851851851851852, "win_rate_random": 0.014814814814814815, "average_game_length": 14.333333333333334}, {"win_rate_mcts": 0.9852941176470589, "win_rate_random": 0.014705882352941176, "average_game_length": 14.323529411764707}, {"win_rate_mcts": 0.9854014598540146, "win_rate_random": 0.014598540145985401, "average_game_length": 14.321167883211679}, {"win_rate_mcts": 0.9855072463768116, "win_rate_random": 0.014492753623188406, "average_game_length": 14.31159420289855}, {"win_rate_mcts": 0.9856115107913669, "win_rate_random": 0.014388489208633094, "average_game_length": 14.266187050359711}, {"win_rate_mcts": 0.9857142857142858, "win_rate_random": 0.014285714285714285, "average_game_length": 14.257142857142858}, {"win_rate_mcts": 0.9858156028368794, "win_rate_random": 0.014184397163120567, "average_game_length": 14.28368794326241}, {"win_rate_mcts": 0.9859154929577465, "win_rate_random": 0.014084507042253521, "average_game_length": 14.274647887323944}, {"win_rate_mcts": 0.986013986013986, "win_rate_random": 0.013986013986013986, "average_game_length": 14.272727272727273}, {"win_rate_mcts": 0.9861111111111112, "win_rate_random": 0.013888888888888888, "average_game_length": 14.277777777777779}, {"win_rate_mcts": 0.9862068965517241, "win_rate_random": 0.013793103448275862, "average_game_length": 14.23448275862069}, {"win_rate_mcts": 0.9863013698630136, "win_rate_random": 0.0136986301369863, "average_game_length": 14.212328767123287}, {"win_rate_mcts": 0.9863945578231292, "win_rate_random": 0.013605442176870748, "average_game_length": 14.210884353741497}, {"win_rate_mcts": 0.9864864864864865, "win_rate_random": 0.013513513513513514, "average_game_length": 14.216216216216216}, {"win_rate_mcts": 0.9865771812080537, "win_rate_random": 0.013422818791946308, "average_game_length": 14.201342281879194}, {"win_rate_mcts": 0.9866666666666667, "win_rate_random": 0.013333333333333334, "average_game_length": 14.18}, {"win_rate_mcts": 0.9867549668874173, "win_rate_random": 0.013245033112582781, "average_game_length": 14.165562913907285}, {"win_rate_mcts": 0.9868421052631579, "win_rate_random": 0.013157894736842105, "average_game_length": 14.18421052631579}, {"win_rate_mcts": 0.9869281045751634, "win_rate_random": 0.013071895424836602, "average_game_length": 14.196078431372548}, {"win_rate_mcts": 0.987012987012987, "win_rate_random": 0.012987012987012988, "average_game_length": 14.214285714285714}, {"win_rate_mcts": 0.9870967741935484, "win_rate_random": 0.012903225806451613, "average_game_length": 14.187096774193549}, {"win_rate_mcts": 0.9871794871794872, "win_rate_random": 0.01282051282051282, "average_game_length": 14.205128205128204}, {"win_rate_mcts": 0.9872611464968153, "win_rate_random": 0.012738853503184714, "average_game_length": 14.165605095541402}, {"win_rate_mcts": 0.9873417721518988, "win_rate_random": 0.012658227848101266, "average_game_length": 14.170886075949367}, {"win_rate_mcts": 0.9874213836477987, "win_rate_random": 0.012578616352201259, "average_game_length": 14.169811320754716}, {"win_rate_mcts": 0.9875, "win_rate_random": 0.0125, "average_game_length": 14.1875}, {"win_rate_mcts": 0.9875776397515528, "win_rate_random": 0.012422360248447204, "average_game_length": 14.149068322981366}, {"win_rate_mcts": 0.9876543209876543, "win_rate_random": 0.012345679012345678, "average_game_length": 14.191358024691358}, {"win_rate_mcts": 0.9877300613496932, "win_rate_random": 0.012269938650306749, "average_game_length": 14.153374233128835}, {"win_rate_mcts": 0.9878048780487805, "win_rate_random": 0.012195121951219513, "average_game_length": 14.207317073170731}, {"win_rate_mcts": 0.9878787878787879, "win_rate_random": 0.012121212121212121, "average_game_length": 14.16969696969697}, {"win_rate_mcts": 0.9879518072289156, "win_rate_random": 0.012048192771084338, "average_game_length": 14.22289156626506}, {"win_rate_mcts": 0.9880239520958084, "win_rate_random": 0.011976047904191617, "average_game_length": 14.25748502994012}, {"win_rate_mcts": 0.9880952380952381, "win_rate_random": 0.011904761904761904, "average_game_length": 14.273809523809524}, {"win_rate_mcts": 0.9881656804733728, "win_rate_random": 0.011834319526627219, "average_game_length": 14.2603550295858}, {"win_rate_mcts": 0.9882352941176471, "win_rate_random": 0.011764705882352941, "average_game_length": 14.264705882352942}, {"win_rate_mcts": 0.9883040935672515, "win_rate_random": 0.011695906432748537, "average_game_length": 14.263157894736842}, {"win_rate_mcts": 0.9883720930232558, "win_rate_random": 0.011627906976744186, "average_game_length": 14.313953488372093}, {"win_rate_mcts": 0.9884393063583815, "win_rate_random": 0.011560693641618497, "average_game_length": 14.289017341040463}, {"win_rate_mcts": 0.9827586206896551, "win_rate_random": 0.017241379310344827, "average_game_length": 14.28735632183908}, {"win_rate_mcts": 0.9828571428571429, "win_rate_random": 0.017142857142857144, "average_game_length": 14.262857142857143}, {"win_rate_mcts": 0.9829545454545454, "win_rate_random": 0.017045454545454544, "average_game_length": 14.232954545454545}, {"win_rate_mcts": 0.9830508474576272, "win_rate_random": 0.01694915254237288, "average_game_length": 14.19774011299435}, {"win_rate_mcts": 0.9831460674157303, "win_rate_random": 0.016853932584269662, "average_game_length": 14.168539325842696}, {"win_rate_mcts": 0.9832402234636871, "win_rate_random": 0.01675977653631285, "average_game_length": 14.167597765363128}, {"win_rate_mcts": 0.9833333333333333, "win_rate_random": 0.016666666666666666, "average_game_length": 14.13888888888889}, {"win_rate_mcts": 0.9834254143646409, "win_rate_random": 0.016574585635359115, "average_game_length": 14.149171270718233}, {"win_rate_mcts": 0.9835164835164835, "win_rate_random": 0.016483516483516484, "average_game_length": 14.175824175824175}, {"win_rate_mcts": 0.9836065573770492, "win_rate_random": 0.01639344262295082, "average_game_length": 14.142076502732241}, {"win_rate_mcts": 0.9836956521739131, "win_rate_random": 0.016304347826086956, "average_game_length": 14.179347826086957}, {"win_rate_mcts": 0.9837837837837838, "win_rate_random": 0.016216216216216217, "average_game_length": 14.167567567567568}, {"win_rate_mcts": 0.9838709677419355, "win_rate_random": 0.016129032258064516, "average_game_length": 14.150537634408602}, {"win_rate_mcts": 0.983957219251337, "win_rate_random": 0.016042780748663103, "average_game_length": 14.117647058823529}, {"win_rate_mcts": 0.9840425531914894, "win_rate_random": 0.015957446808510637, "average_game_length": 14.143617021276595}, {"win_rate_mcts": 0.9841269841269841, "win_rate_random": 0.015873015873015872, "average_game_length": 14.153439153439153}, {"win_rate_mcts": 0.9842105263157894, "win_rate_random": 0.015789473684210527, "average_game_length": 14.157894736842104}, {"win_rate_mcts": 0.9842931937172775, "win_rate_random": 0.015706806282722512, "average_game_length": 14.188481675392671}, {"win_rate_mcts": 0.984375, "win_rate_random": 0.015625, "average_game_length": 14.192708333333334}, {"win_rate_mcts": 0.9844559585492227, "win_rate_random": 0.015544041450777202, "average_game_length": 14.202072538860104}, {"win_rate_mcts": 0.9845360824742269, "win_rate_random": 0.015463917525773196, "average_game_length": 14.195876288659793}, {"win_rate_mcts": 0.9846153846153847, "win_rate_random": 0.015384615384615385, "average_game_length": 14.174358974358974}, {"win_rate_mcts": 0.9846938775510204, "win_rate_random": 0.015306122448979591, "average_game_length": 14.209183673469388}, {"win_rate_mcts": 0.9847715736040609, "win_rate_random": 0.015228426395939087, "average_game_length": 14.197969543147208}, {"win_rate_mcts": 0.9848484848484849, "win_rate_random": 0.015151515151515152, "average_game_length": 14.232323232323232}, {"win_rate_mcts": 0.9849246231155779, "win_rate_random": 0.01507537688442211, "average_game_length": 14.231155778894472}, {"win_rate_mcts": 0.985, "win_rate_random": 0.015, "average_game_length": 14.205}]}